sagah/__init__.py
sagah/saga.py
sagah-0.1.0.dist-info/LICENSE.md
sagah-0.1.0.dist-info/WHEEL
sagah-0.1.0.dist-info/METADATA
sagah-0.1.0.dist-info/RECORD
