Metadata-Version: 2.1
Name: sagah
Version: 0.1.0
Summary: Orchestrated, async sagas in Python
Home-page: https://github.com/NarrativeScience/sagah
License: BSD-3-Clause
Author: Jonathan Drake
Author-email: jdrake@narrativescience.com
Requires-Python: >=3.6.5,<4.0.0
Classifier: License :: OSI Approved :: BSD License
Classifier: Programming Language :: Python :: 3
Classifier: Programming Language :: Python :: 3.7
Classifier: Programming Language :: Python :: 3.8
Classifier: Programming Language :: Python :: 3.9
Project-URL: Repository, https://github.com/NarrativeScience/sagah
